ba_whatsapp_api_client_python/API.py
ba_whatsapp_api_client_python/__init__.py
ba_whatsapp_api_client_python/response.py
ba_whatsapp_api_client_python/tools/__init__.py
ba_whatsapp_api_client_python/tools/account.py
ba_whatsapp_api_client_python/tools/device.py
ba_whatsapp_api_client_python/tools/groups.py
ba_whatsapp_api_client_python/tools/journals.py
ba_whatsapp_api_client_python/tools/marking.py
ba_whatsapp_api_client_python/tools/queues.py
ba_whatsapp_api_client_python/tools/receiving.py
ba_whatsapp_api_client_python/tools/sending.py
ba_whatsapp_api_client_python/tools/serviceMethods.py
ba_whatsapp_api_client_python/tools/webhooks.py
ba_whatsapp_api_client_python-0.0.33.dist-info/LICENSE
ba_whatsapp_api_client_python-0.0.33.dist-info/METADATA
ba_whatsapp_api_client_python-0.0.33.dist-info/WHEEL
ba_whatsapp_api_client_python-0.0.33.dist-info/top_level.txt
ba_whatsapp_api_client_python-0.0.33.dist-info/RECORD
